setup.cfg
setup.py
Lab_3/__init__.py
Lab_3/helpers/constants.py
Lab_3/helpers/functions.py
Lab_3/serializers/jsonserializer.py
Lab_3/serializers/xmlserializer.py
jxser.egg-info/PKG-INFO
jxser.egg-info/SOURCES.txt
jxser.egg-info/dependency_links.txt
jxser.egg-info/not-zip-safe
jxser.egg-info/top_level.txt